{
	"info": {
		"_postman_id": "51cbd7f6-5dce-4e7d-b5da-44e771e0a066",
		"name": "happy_moons",
		"schema": "https://schema.getpostman.com/json/collection/v2.1.0/collection.json",
		"_exporter_id": "37232824"
	},
	"item": [
		{
			"name": "get_categories",
			"request": {
				"method": "GET",
				"header": [],
				"url": {
					"raw": "localhost:3000/categories",
					"host": [
						"localhost"
					],
					"port": "3000",
					"path": [
						"categories"
					]
				}
			},
			"response": []
		},
		{
			"name": "get_id_categories",
			"request": {
				"method": "GET",
				"header": [],
				"url": {
					"raw": "localhost:3000/categories/:id",
					"host": [
						"localhost"
					],
					"port": "3000",
					"path": [
						"categories",
						":id"
					],
					"variable": [
						{
							"key": "id",
							"value": "1"
						}
					]
				}
			},
			"response": []
		},
		{
			"name": "post_categories",
			"request": {
				"method": "POST",
				"header": [],
				"body": {
					"mode": "raw",
					"raw": "{\r\n    \"name\" : \"Kebab\",\r\n    \"description\" : \"kıyma et yemegidir.\"\r\n}",
					"options": {
						"raw": {
							"language": "json"
						}
					}
				},
				"url": {
					"raw": "localhost:3000/categories",
					"host": [
						"localhost"
					],
					"port": "3000",
					"path": [
						"categories"
					]
				}
			},
			"response": []
		},
		{
			"name": "patch_id_categories",
			"request": {
				"method": "PATCH",
				"header": [],
				"url": {
					"raw": "localhost:3000/categories/:id",
					"host": [
						"localhost"
					],
					"port": "3000",
					"path": [
						"categories",
						":id"
					],
					"variable": [
						{
							"key": "id",
							"value": "1"
						}
					]
				}
			},
			"response": []
		},
		{
			"name": "deleted_id_categories",
			"request": {
				"method": "DELETE",
				"header": [],
				"url": {
					"raw": "localhost:3000/categories/:id",
					"host": [
						"localhost"
					],
					"port": "3000",
					"path": [
						"categories",
						":id"
					],
					"variable": [
						{
							"key": "id",
							"value": "1"
						}
					]
				}
			},
			"response": []
		},
		{
			"name": "get_products",
			"protocolProfileBehavior": {
				"disableBodyPruning": true
			},
			"request": {
				"method": "GET",
				"header": [],
				"body": {
					"mode": "raw",
					"raw": "{\r\n    \"category_id\" : 3,\r\n    \"name\" : \"Kebab\",\r\n    \"description\": \"Urfa Kebabı\",\r\n    \"price\" : 131\r\n}",
					"options": {
						"raw": {
							"language": "json"
						}
					}
				},
				"url": {
					"raw": "localhost:3000/products",
					"host": [
						"localhost"
					],
					"port": "3000",
					"path": [
						"products"
					]
				}
			},
			"response": []
		},
		{
			"name": "get_id_products",
			"protocolProfileBehavior": {
				"disableBodyPruning": true
			},
			"request": {
				"method": "GET",
				"header": [],
				"body": {
					"mode": "raw",
					"raw": "{\r\n    \"category_id\" : 3,\r\n    \"name\" : \"Kebab\",\r\n    \"description\": \"Urfa Kebabı\",\r\n    \"price\" : 131\r\n}",
					"options": {
						"raw": {
							"language": "json"
						}
					}
				},
				"url": {
					"raw": "localhost:3000/products/:id",
					"host": [
						"localhost"
					],
					"port": "3000",
					"path": [
						"products",
						":id"
					],
					"variable": [
						{
							"key": "id",
							"value": "1"
						}
					]
				}
			},
			"response": []
		},
		{
			"name": "post_products",
			"request": {
				"method": "POST",
				"header": [],
				"url": {
					"raw": "localhost:3000/products",
					"host": [
						"localhost"
					],
					"port": "3000",
					"path": [
						"products"
					]
				}
			},
			"response": []
		},
		{
			"name": "patch_id_products",
			"request": {
				"method": "PATCH",
				"header": [],
				"url": {
					"raw": "localhost:3000/products/:id",
					"host": [
						"localhost"
					],
					"port": "3000",
					"path": [
						"products",
						":id"
					],
					"variable": [
						{
							"key": "id",
							"value": "1"
						}
					]
				}
			},
			"response": []
		},
		{
			"name": "deleted_id_products",
			"request": {
				"method": "DELETE",
				"header": [],
				"url": {
					"raw": "localhost:3000/products/:id",
					"host": [
						"localhost"
					],
					"port": "3000",
					"path": [
						"products",
						":id"
					],
					"variable": [
						{
							"key": "id",
							"value": "1"
						}
					]
				}
			},
			"response": []
		},
		{
			"name": "get_ingredients",
			"request": {
				"method": "GET",
				"header": [],
				"url": {
					"raw": "localhost:3000/ingredients",
					"host": [
						"localhost"
					],
					"port": "3000",
					"path": [
						"ingredients"
					]
				}
			},
			"response": []
		},
		{
			"name": "get_id_ingredients",
			"request": {
				"method": "GET",
				"header": [],
				"url": {
					"raw": "localhost:3000/ingredients/:id",
					"host": [
						"localhost"
					],
					"port": "3000",
					"path": [
						"ingredients",
						":id"
					],
					"variable": [
						{
							"key": "id",
							"value": "1"
						}
					]
				}
			},
			"response": []
		},
		{
			"name": "post_ingredients",
			"request": {
				"method": "POST",
				"header": [],
				"body": {
					"mode": "raw",
					"raw": "{\r\n    \"name\" : \"Kebab\",\r\n    \"is_allergen\" : false\r\n}",
					"options": {
						"raw": {
							"language": "json"
						}
					}
				},
				"url": {
					"raw": "localhost:3000/ingredients",
					"host": [
						"localhost"
					],
					"port": "3000",
					"path": [
						"ingredients"
					]
				}
			},
			"response": []
		},
		{
			"name": "patch_id_ingredients",
			"request": {
				"method": "PATCH",
				"header": [],
				"url": {
					"raw": "localhost:3000/ingredients/:id",
					"host": [
						"localhost"
					],
					"port": "3000",
					"path": [
						"ingredients",
						":id"
					],
					"variable": [
						{
							"key": "id",
							"value": "1"
						}
					]
				}
			},
			"response": []
		},
		{
			"name": "deleted_id_ingredients",
			"request": {
				"method": "DELETE",
				"header": [],
				"url": {
					"raw": "localhost:3000/ingredients/:id",
					"host": [
						"localhost"
					],
					"port": "3000",
					"path": [
						"ingredients",
						":id"
					],
					"variable": [
						{
							"key": "id",
							"value": "1"
						}
					]
				}
			},
			"response": []
		}
	]
}